bintray_upload.py
setup.py
bintray_upload.egg-info/PKG-INFO
bintray_upload.egg-info/SOURCES.txt
bintray_upload.egg-info/dependency_links.txt
bintray_upload.egg-info/entry_points.txt
bintray_upload.egg-info/pbr.json
bintray_upload.egg-info/requires.txt
bintray_upload.egg-info/top_level.txt