Metadata-Version: 1.0
Name: bintray-upload
Version: 0.1.1
Summary: Simple BinTray utility for uploading Debian packages.
Home-page: https://github.com/joshmarshall/bintray
Author: Josh Marshall
Author-email: catchjosh@gmail.com
License: http://www.apache.org/licenses/LICENSE-2.0
Platform: UNKNOWN
